{"0": ["T000000", "나무젓가락"], "1": ["T000001", "cd"], "2": ["T000002", "헤어드라이어"], "3": ["T000003", "칫솔"], "4": ["T000004", "은박보냉백"], "5": ["T000005", "영수증"], "6": ["T000006", "알약"], "7": ["T000007", "아이스팩"], "8": ["T000008", "스파우트파우치"], "9": ["T000009", "마스크"], "10": ["T000010", "고무장갑"], "11": ["T000011", "건전지"], "12": ["T000012", "유리"], "13": ["T000013", "캔"], "14": ["T000014", "계란판"], "15": ["T000015", "종이"], "16": ["T000016", "플라스틱통"], "17": ["T000017", "PET"], "18": ["T000018", "드라이버"], "19": ["T000019", "플라스틱"], "20": ["T000020", "요구르트병"], "21": ["T000021", "종이팩"], "22": ["T000022", "스프링노트"], "23": ["T000023", "상자"], "24": ["T000024", "unknown"]}